revpipyload/__init__.py
revpipyload/__main__.py
revpipyload/helper.py
revpipyload/logsystem.py
revpipyload/mqttserver.py
revpipyload/picontrolserver.py
revpipyload/plcsystem.py
revpipyload/procimgserver.py
revpipyload/proginit.py
revpipyload/revpipyload.py
revpipyload/secure_installation.py
revpipyload/testsystem.py
revpipyload/watchdogs.py
revpipyload/xrpcserver.py
revpipyload/shared/__init__.py
revpipyload/shared/ipaclmanager.py
revpipyload-0.11.0.dist-info/LICENSE.txt
revpipyload-0.11.0.dist-info/METADATA
revpipyload-0.11.0.dist-info/WHEEL
revpipyload-0.11.0.dist-info/entry_points.txt
revpipyload-0.11.0.dist-info/top_level.txt
revpipyload-0.11.0.dist-info/RECORD
