Metadata-Version: 2.1
Name: revpipyload
Version: 0.11.0
Summary: PLC Loader für Python-Projekte auf den RevolutionPi
Home-page: https://revpimodio.org/revpipyplc/
Author: Sven Sager
Author-email: akira@narux.de
Maintainer: Sven Sager
Maintainer-email: akira@revpimodio.org
License: GPLv2
Keywords: revpi,revolution pi,revpimodio,plc
Platform: revolution pi
Classifier: Development Status :: 5 - Production/Stable
Classifier: Environment :: No Input/Output (Daemon)
Classifier: Intended Audience :: Manufacturing
Classifier: License :: OSI Approved :: GNU General Public License v2 (GPLv2)
Classifier: Operating System :: POSIX :: Linux
Classifier: Topic :: System :: Operating System
License-File: LICENSE.txt
Requires-Dist: paho-mqtt >=1.4.0
Requires-Dist: revpimodio2 >=2.7.0rc2
